pyspark_test.py
pyspark_test-0.2.0.dist-info/LICENSE
pyspark_test-0.2.0.dist-info/METADATA
pyspark_test-0.2.0.dist-info/WHEEL
pyspark_test-0.2.0.dist-info/top_level.txt
pyspark_test-0.2.0.dist-info/RECORD
