Metadata-Version: 2.1
Name: pyspark-test
Version: 0.2.0
Summary: Check that left and right spark DataFrame are equal.
Home-page: https://github.com/debugger24/pyspark-test
Author: Rahul Kumar
Author-email: rahulcomp24@gmail.com
License: Apache Software License (Apache 2.0)
Keywords: assert pyspark unit test testing compare
Platform: UNKNOWN
License-File: LICENSE
Requires-Dist: pyspark (>=2.1.2)
